pgmock/__init__.py
pgmock/config.py
pgmock/exceptions.py
pgmock/mocker.py
pgmock/render.py
pgmock/selector.py
pgmock/version.py
pgmock/tests/__init__.py
pgmock/tests/test_config.py
pgmock/tests/test_examples.py
pgmock/tests/test_interface.py
pgmock/tests/test_mocker.py
pgmock/tests/test_render.py
pgmock-1.3.7.dist-info/DESCRIPTION.rst
pgmock-1.3.7.dist-info/METADATA
pgmock-1.3.7.dist-info/RECORD
pgmock-1.3.7.dist-info/WHEEL
pgmock-1.3.7.dist-info/metadata.json
pgmock-1.3.7.dist-info/pbr.json
pgmock-1.3.7.dist-info/top_level.txt
