Metadata-Version: 2.0
Name: pgmock
Version: 1.3.7
Summary: A library for mocking Postgres queries
Home-page: https://github.com/CloverHealth/pgmock
Author: Clover Health
Author-email: oss@cloverhealth.com
License: BSD 3-Clause
Platform: UNKNOWN
Classifier: Topic :: Internet :: WWW/HTTP :: Dynamic Content
Classifier: Intended Audience :: Developers
Classifier: Programming Language :: Python
Classifier: Programming Language :: Python :: 3
Classifier: Development Status :: 4 - Beta
Classifier: Operating System :: OS Independent
Requires-Dist: sqlalchemy
